README.rst
aiqterminal.py
setup.py
aiqterminal.egg-info/PKG-INFO
aiqterminal.egg-info/SOURCES.txt
aiqterminal.egg-info/dependency_links.txt
aiqterminal.egg-info/entry_points.txt
aiqterminal.egg-info/not-zip-safe
aiqterminal.egg-info/requires.txt
aiqterminal.egg-info/top_level.txt