Metadata-Version: 1.0
Name: aiqterminal
Version: 0.1
Summary: Interactive shell for administrating a AIQ8 platform server
Home-page: UNKNOWN
Author: Erik Lundberg
Author-email: lundbergerik@gmail.com
License: UNKNOWN
Keywords: aiq8,appeariq
Platform: UNKNOWN
